mdsasa_bolt-1.2.0.dist-info/METADATA
mdsasa_bolt-1.2.0.dist-info/WHEEL
mdsasa_bolt-1.2.0.dist-info/licenses/LICENSE
mdsasa_bolt/__init__.py
mdsasa_bolt/analysis.py
mdsasa_bolt/inference.py
mdsasa_bolt/plumber.cpython-311-darwin.so
mdsasa_bolt-1.2.0.dist-info/RECORD
