Metadata-Version: 2.4
Name: mdsasa_bolt
Version: 1.2.0
Requires-Dist: biopython>=1.85
Requires-Dist: freesasa>=2.2.1
Requires-Dist: mdanalysis>=2.9.0
Requires-Dist: numpy>=2.3.1
Requires-Dist: pytest>=8.4.1
Requires-Dist: rust-sasa-python>=0.2.5
License-File: LICENSE
Summary: This library allows the calculation of a solvent-accessible-surface area of a trajectory
Keywords: molecular simulations,science,bioinformatics
Author-email: Maxwell Campbell <max@hearthindustries.io>
Maintainer-email: Maxwell Campbell <max@hearthindustries.io>
License-Expression: GPL-2.0
Requires-Python: >=3.11
